LICENSE.txt
README.md
setup.cfg
setup.py
venv2docker/__init__.py
venv2docker/dockerize.py
venv2docker/exceptions.py
venv2docker/venv_py_props.py
venv2docker.egg-info/PKG-INFO
venv2docker.egg-info/SOURCES.txt
venv2docker.egg-info/dependency_links.txt
venv2docker.egg-info/entry_points.txt
venv2docker.egg-info/requires.txt
venv2docker.egg-info/top_level.txt