Metadata-Version: 2.1
Name: venv2docker
Version: 1.0
Summary: Convert virtual env to docker container!
Home-page: https://github.com/nowtilous/Dockerize-Venv
Author: McLovin
Author-email: e.e@e.com
License: MIT
Keywords: docker,virtualenv,venv,converter
Platform: UNKNOWN
License-File: LICENSE.txt
